taskaway/__init__.py
taskaway/column_layout_screen.py
taskaway/constants.py
taskaway/main.py
taskaway/taskaway.tcss
taskaway/taskaway_types.py
taskaway/utils.py
taskaway-0.4.0.dist-info/LICENSE
taskaway-0.4.0.dist-info/METADATA
taskaway-0.4.0.dist-info/WHEEL
taskaway-0.4.0.dist-info/entry_points.txt
taskaway-0.4.0.dist-info/RECORD
