Metadata-Version: 2.1
Name: taskaway
Version: 0.4.0
Summary: A terminal user interface for TaskWarrior
Requires-Python: >=3.9,<4.0
Classifier: Programming Language :: Python :: 3
Classifier: Programming Language :: Python :: 3.9
Classifier: Programming Language :: Python :: 3.10
Classifier: Programming Language :: Python :: 3.11
Classifier: Programming Language :: Python :: 3.12
Requires-Dist: tasklib (>=2.5,<3.0)
Requires-Dist: textual (>=2.0,<3.0)
